<?xml version="1.0" encoding="utf-8"?>
<object name="sitter" meta_type="Dexterity Container">
 <criteria>
  <criterion name="criterion-experience">
   <property name="widget">checkbox</property>
   <property name="title">Erfahrung</property>
   <property name="index">experience</property>
   <property name="operator">or</property>
   <property name="operator_visible">False</property>
   <property name="vocabulary">collective.sitter.Experiences</property>
   <property name="position">top</property>
   <property name="section">default</property>
   <property name="hidden">False</property>
   <property name="custom_css">expandable-checkboxlist</property>
   <property name="count">True</property>
   <property name="sortcountable">False</property>
   <property name="hidezerocount">False</property>
   <property name="maxitems">10</property>
   <property name="sortreversed">False</property>
  </criterion>
  <criterion name="criterion-qualification">
   <property name="widget">checkbox</property>
   <property name="title">Qualifikation</property>
   <property name="index">qualification</property>
   <property name="operator">or</property>
   <property name="operator_visible">False</property>
   <property name="vocabulary">collective.sitter.Qualifications</property>
   <property name="position">top</property>
   <property name="section">default</property>
   <property name="hidden">False</property>
   <property name="custom_css">expandable-checkboxlist</property>
   <property name="count">True</property>
   <property name="sortcountable">False</property>
   <property name="hidezerocount">False</property>
   <property name="maxitems">10</property>
   <property name="sortreversed">False</property>
  </criterion>
  <criterion name="criterion-mobility">
   <property name="widget">checkbox</property>
   <property name="title">Mobilität</property>
   <property name="index">mobility</property>
   <property name="operator">or</property>
   <property name="operator_visible">False</property>
   <property name="vocabulary">collective.taxonomy.mobility</property>
   <property name="position">top</property>
   <property name="section">default</property>
   <property name="hidden">False</property>
   <property name="custom_css">expandable-checkboxlist</property>
   <property name="count">True</property>
   <property name="sortcountable">False</property>
   <property name="hidezerocount">False</property>
   <property name="maxitems">10</property>
   <property name="sortreversed">False</property>
  </criterion>
  <criterion name="criterion-language">
   <property name="widget">checkbox</property>
   <property name="title">Sprache</property>
   <property name="index">language</property>
   <property name="operator">or</property>
   <property name="operator_visible">False</property>
   <property name="vocabulary">collective.taxonomy.language</property>
   <property name="position">top</property>
   <property name="section">default</property>
   <property name="hidden">False</property>
   <property name="custom_css">expandable-checkboxlist</property>
   <property name="count">True</property>
   <property name="sortcountable">False</property>
   <property name="hidezerocount">False</property>
   <property name="maxitems">10</property>
   <property name="sortreversed">False</property>
  </criterion>
  <criterion name="criterion-portaltype">
   <property name="widget">checkbox</property>
   <property name="title">Portal type</property>
   <property name="index">portal_type</property>
   <property name="operator">or</property>
   <property name="operator_visible">False</property>
   <property name="vocabulary">eea.faceted.vocabularies.FacetedPortalTypes</property>
   <property name="catalog"></property>
   <property name="default">
    <element value="sitter"/>
   </property>
   <property name="position">right</property>
   <property name="section">default</property>
   <property name="hidden">True</property>
   <property name="custom_css"></property>
   <property name="count">True</property>
   <property name="sortcountable">False</property>
   <property name="hidezerocount">False</property>
   <property name="maxitems">5</property>
   <property name="sortreversed">True</property>
  </criterion>
  <criterion name="criteria">
   <property name="widget">criteria</property>
   <property name="title">Current search</property>
   <property name="position">center</property>
   <property name="section">default</property>
   <property name="hidden">False</property>
   <property name="custom_css"></property>
  </criterion>
  <criterion name="criterion-resultsperpage">
   <property name="widget">resultsperpage</property>
   <property name="title">Results per page</property>
   <property name="default">20</property>
   <property name="position">right</property>
   <property name="section">default</property>
   <property name="hidden">True</property>
   <property name="custom_css"></property>
   <property name="start">0</property>
   <property name="end">200</property>
   <property name="step">10</property>
  </criterion>
  <criterion name="criterion-sorting">
   <property name="widget">sorting</property>
   <property name="title">Sort on</property>
   <property name="vocabulary"></property>
   <property name="default">modified</property>
   <property name="position">right</property>
   <property name="section">default</property>
   <property name="hidden">True</property>
   <property name="custom_css"></property>
  </criterion>
  <criterion name="criterion-path">
   <property name="widget">path</property>
   <property name="title">Path</property>
   <property name="index">path</property>
   <property name="default">SITTERFOLDER</property>
   <property name="depth">0</property>
   <property name="position">right</property>
   <property name="section">default</property>
   <property name="hidden">True</property>
  </criterion>
 </criteria>
</object>
